prais/__init__.py
prais-0.1.0.dist-info/METADATA
prais-0.1.0.dist-info/WHEEL
prais-0.1.0.dist-info/licenses/LICENSE
prais-0.1.0.dist-info/RECORD
