Metadata-Version: 2.4
Name: prais
Version: 0.1.0
Summary: A Python package
Project-URL: Homepage, https://github.com/praison/prais
Author: Praison
License: MIT License
License-File: LICENSE
Classifier: License :: OSI Approved :: MIT License
Classifier: Operating System :: OS Independent
Classifier: Programming Language :: Python :: 3
Requires-Python: >=3.6
